Metadata-Version: 2.1
Name: spower
Version: 0.2.4
Summary: Free searcher with python, no API keys are required
Author: MishaKorzhik_He1Zen
Author-email: developer.mishakorzhik@gmail.com
License: Apache 2.0
Project-URL: Sponsor, https://www.buymeacoffee.com/mishakorzik
Keywords: search,google,duck,duckduckgo,searcher,shodan,api,easy,pip,pypi,dork,dorks,dorking
Classifier: Development Status :: 5 - Production/Stable
Classifier: License :: OSI Approved :: Apache Software License
Classifier: Natural Language :: English
Classifier: Operating System :: OS Independent
Classifier: Programming Language :: Python
Classifier: Programming Language :: Python :: 3
Classifier: Programming Language :: Python :: 3.4
Classifier: Programming Language :: Python :: 3.5
Classifier: Programming Language :: Python :: 3.6
Classifier: Programming Language :: Python :: 3.7
Classifier: Programming Language :: Python :: 3.8
Classifier: Programming Language :: Python :: 3.9
Classifier: Programming Language :: Python :: 3.10
Classifier: Programming Language :: Python :: 3.11
Classifier: Programming Language :: Python :: Implementation :: CPython
Classifier: Programming Language :: Python :: Implementation :: PyPy
Classifier: Topic :: Software Development :: Libraries
Requires-Python: >=3.4
